document_translator/__init__.py
document_translator/translate.py
document_translator-0.1.3.dist-info/METADATA
document_translator-0.1.3.dist-info/WHEEL
document_translator-0.1.3.dist-info/top_level.txt
document_translator-0.1.3.dist-info/RECORD
