Metadata-Version: 2.1
Name: document-translator
Version: 0.1.3
Summary: A simple and fast translator for translating documents in google translate supported languages
Home-page: 
Author: Nirmal Patel
Author-email: nirmalpatel1705@gmail.com
Classifier: Programming Language :: Python :: 3.11
Classifier: License :: OSI Approved :: MIT License
Classifier: Operating System :: OS Independent
Requires-Python: >=3.6
Requires-Dist: selenium
